hamming_sim/__init__.py
hamming_sim/hamming_sim.cpp
hamming_sim/hamming_sim.cpython-39-x86_64-linux-gnu.so
hamming_sim/utils.py
hamming_sim_pytorch-0.1.4.dist-info/LICENSE
hamming_sim_pytorch-0.1.4.dist-info/METADATA
hamming_sim_pytorch-0.1.4.dist-info/WHEEL
hamming_sim_pytorch-0.1.4.dist-info/RECORD
