Metadata-Version: 2.3
Name: hamming-sim-pytorch
Version: 0.1.4
Summary: A PyTorch extension for hamming similarity optimized for CPU usage.
License: MIT
Author: Yashasvi Ranawat
Author-email: yashasvi.ranawat@iprally.com
Maintainer: Berker Peksag
Maintainer-email: berker.peksag@iprally.com
Requires-Python: >=3.9,<4.0
Classifier: License :: OSI Approved :: MIT License
Classifier: Programming Language :: Python :: 3
Classifier: Programming Language :: Python :: 3.9
Classifier: Programming Language :: Python :: 3.10
Classifier: Programming Language :: Python :: 3.11
Classifier: Programming Language :: Python :: 3.12
Classifier: Programming Language :: Python :: 3.13
Requires-Dist: numpy (>=1.22,<1.23)
Requires-Dist: torch (==1.13.1)
